{"type":"Feature","id":"node/4955426411","properties":{"addr:city":"Zunzgen","addr:housenumber":"124","addr:postcode":"4455","addr:street":"Horen","email":"michele.bauen@gmail.com","name":"Hof Horen","note":"Rindfeisch, Hühnereier, Gemüse und Salate, Apfelsaft, Sirup, Honig, Konfitüren (Erdbeeren, Kirschen)\nGartenarbeiten, Geschenkartikel, Geschenkkörbe,\nAnlässe für Gesellschaften.","opening_hours":"nach Vereinbarung","operator":"Familie Kurt Mohler","organic":"no","phone":"+41 61 971 70 44","shop":"farm","source":"https://hofsuche.vomhof.ch/de/farm/hof-horen-8103","website":"https://www.hofhoren.com/","id":"node/4955426411"},"geometry":{"type":"Point","coordinates":[7.8017759,47.4469107]}}