{"type":"Feature","properties":{"email":"biohof@gmx.ch","note":"Gem체se, Beeren, Milch, Wein, Sirup, Konfit체re, Obst, Eier, Spirituosen, Honig, G채stebewirtung","Betreiber":"Hugo und Rita Schneitter-Markwalder","Biologisch":"ja","Telefon":"+41 32 641 26 69","shop":"farm","Quelle":"https://www.knospehof.ch/bio/biohof-chuehmoos"},"name":"Biohof Ch체ehmoos","address":{"street":"Oberdorfstrasse","housenumber":"16","postcode":"4516","city":"Lommiswil"},"opening_hours":"Selbstbedienung, Oeffnungszeiten: Fr.+Sa: 10-18 Uhr. Backwaren am Freitag ab 15.00 Uhr.","website":"http://www.biobuurehof.ch/","property":"farm","id":"node/4958420997","geometry":{"type":"Point","coordinates":[7.4764375,47.2300291]}}