{"type":"Feature","properties":{"email":"thomasstohler@bluewin.ch","note":"Kirschen, Zwetschgen, Äpfel u.a. Lederäpfel, Aprikosen, Schnaps.","Betreiber":"Thomas Stohler","Biologisch":"no","Telefon":"+41 61 941 15 74","shop":"farm","Quelle":"http://www.hochstamm-laebt.ch/index.php/produkte/direktverkauf"},"name":"Hof Hinterfeld","address":{"street":"Hinterfeld","housenumber":"108","postcode":"4425","city":"Titterten"},"opening_hours":"nach Vereinbarung","property":"farm","id":"node/4956924114","geometry":{"type":"Point","coordinates":[7.7152313,47.3956695]}}