{"type":"Feature","id":"node/12046231113","properties":{"contact:phone":"+49 7123 60847","contact:website":"https://www.metzingen.de/de/Leben-Rathaus/Wirtschaft/Obstbau-Wald-und-Landwirtschaft/Staedtischer-Obstbaubetrieb","name":"Städtischer Obstbaubetrieb","opening_hours":"Sep-Jan Th 15:00-17:00; Sep-Jan Fr 12:00-17:00; Feb-Aug Th 15:00-17:00; PH closed","organic":"only","produce":"apple juice;apple;apple chips;grape;pear;cherry","shop":"farm","id":"node/12046231113"},"geometry":{"type":"Point","coordinates":[9.2968096,48.5524242]}}