{"type":"Feature","id":"way/540063563","properties":{"addr:city":"Adenbüttel","addr:country":"DE","addr:housenumber":"17","addr:postcode":"38528","addr:street":"Gifhorner Straße","building":"barn","name":"Thörmanns Hofladen","opening_hours":"Tu-Fr 09:00-13:00; Sa 08:00-13:00; We-Fr 15:00-18:00","operator":"Jörn Thörmann","phone":"(0 53 04) 91 16 04","shop":"farm","website":"http://www.hofladen-adenbuettel.de/","id":"way/540063563"},"geometry":{"type":"Point","coordinates":[10.4530005,52.3849027]}}