{"type":"Feature","id":"node/5928514361","properties":{"addr:city":"Basel","addr:housenumber":"20","addr:postcode":"4051","addr:street":"Steinentorberg","amenity":"marketplace","email":"info@altemarkthalle.ch","name":"Juramarkt","note":"Monatsmarkt mit regionalen Produkten","opening_hours":"Sa[1] 10:00-15:00","operator":"Markthallen AG","source":"https://www.altemarkthalle.ch","website":"https://www.altemarkthalle.ch/angebot/juramahttps://www.altemarkthalle.ch/angebot/frischwarenmaerkte/juramarkt-1/rkt/","id":"node/5928514361"},"geometry":{"type":"Point","coordinates":[7.5869289,47.5491815]}}