{"type":"Feature","id":"node/1372128949","properties":{"addr:city":"Villigen","addr:housenumber":"4","addr:postcode":"5234","addr:street":"Schürmattstrasse","email":"gemuesebau@schwarz.ch","name":"Hof Max Schwarz AG","note":"Gemüse; z.B. Eisbergsalat, Bundzwiebeln, Lauch. Tomaten (Rispen, Cherry, Mini Marzini, Cuor di Bue usw.) Nüsslisalat, Gurken, Zucchetti, Lavata.","opening_hours":"Fr 16:30-18:30","operator":"Toni Suter Max Schwarz AG","organic":"no","phone":"+41 56 297 87 17","shop":"farm","source":"https://www.vomhof.ch/hof-suche/detailansicht/farm/max-schwarz-ag/","website":"https://www.schwarz.ch/de/gemuesebau","id":"node/1372128949"},"geometry":{"type":"Point","coordinates":[8.2177003,47.5268683]}}