{"type":"Feature","id":"node/1845019503","properties":{"addr:city":"Binz","addr:housenumber":"2","addr:postcode":"8122","addr:street":"Zollikonstrasse","name":"Milchlädeli Weber","opening_hours":"Tu-Sa 08:45-12:15, 15:00-19:00; Su 15:00-19:00","operator":"Weber Comestibles","organic":"yes","payment:cards":"yes","payment:cash":"yes","payment:contactless":"yes","phone":"+41 44 887 73 76","shop":"farm","website":"https://www.webercomestibles.ch/","id":"node/1845019503"},"geometry":{"type":"Point","coordinates":[8.6279389,47.3568979]}}