{"type":"Feature","id":"node/2500027619","properties":{"addr:city":"Überlingen","addr:country":"DE","addr:housenumber":"1","addr:postcode":"88662","addr:street":"Hagenweiler","addr:suburb":"Lippertsreute","name":"Hagenweiler Hof","opening_hours":"Mo-Th 17:00-19:30; Fr 14:00-19:00","phone":"+49 7553 7529","produce":"Milch;Eier;Walnüsse;Käse;Wurst;Rindfleisch;Schweinefleisch;Honig;Obst;Bier;Schnaps","shop":"farm","source":"Maps4BW, LGL, www.lgl-bw.de","website":"https://www.hagenweilerhof.de/","id":"node/2500027619"},"geometry":{"type":"Point","coordinates":[9.2245115,47.795503]}}