{"type":"Feature","id":"way/321151358","properties":{"addr:city":"Oberhausen-Rheinhausen","addr:country":"DE","addr:housenumber":"67","addr:postcode":"68794","addr:street":"Hauptstraße","addr:suburb":"Rheinhausen","level":"0","name":"Spargelhof Kollmar","opening_hours":"closed ||Mo-Fr 8:00-13:00, 15:00-18:00; Sa-Su 8:00-13:00 open \"während der Spargelsaison\"","seasonal":"spring","shop":"farm","wheelchair":"no","id":"way/321151358"},"geometry":{"type":"Point","coordinates":[8.4731246,49.2778544]}}