{"type":"Feature","id":"node/2426508183","properties":{"addr:city":"Edingen-Neckarhausen","addr:country":"DE","addr:housenumber":"30","addr:postcode":"68535","addr:street":"Grenzhöfer Straße","addr:suburb":"Edingen","contact:email":"info@heldenhof.de","contact:fax":"+49 6203 9583121","contact:phone":"+49 6203 85635","contact:website":"https://www.heldenhof.de","name":"HelDenHofladen","opening_hours":"Mo-Fr 09:00-12:30; Th,Fr15:00-18:00; Sa 08:30-12:30","operator":"Helmut und Dennis Koch","produce":"chicken;egg;pork;berries;vegetable","shop":"farm","id":"node/2426508183"},"geometry":{"type":"Point","coordinates":[8.6114364,49.4448723]}}