{"type":"Feature","id":"node/7457077104","properties":{"addr:city":"Lampertheim","addr:housenumber":"22","addr:postcode":"67450","addr:street":"Rue de Mundolsheim","contact:facebook":"https://www.facebook.com/FERMEJenner/","delivery:covid19":"yes","description:covid19":"Sur commande par téléphone. Asperges ( mayonnaise, jambon,vin d'alsace), rhubarbe, oeufs, pomme de terre.","name":"Ferme Jenner","opening_hours:covid19":"10:00-12:00,13:30-19:00","phone":"+33388201559","shop":"farm","takeaway:covid19":"yes","id":"node/7457077104"},"geometry":{"type":"Point","coordinates":[7.7015433,48.6482914]}}