{"type":"Feature","id":"node/13234202068","properties":{"addr:city":"Rottenacker","addr:housenumber":"1","addr:postcode":"89616","addr:street":"Neumühle","email":"info@neumuehle-rottenacker.de","mobile":"+49 157 30122913","name":"Neumühle Rottenacker","opening_hours":"Mo, Th, Fr 09:00-12:00, 14:00-17:00; Sa 09:00-12:00","payment:cash":"yes","phone":"+49 7393 2972","shop":"farm","website":"https://neumuehle-rottenacker.de/","wheelchair":"yes","id":"node/13234202068"},"geometry":{"type":"Point","coordinates":[9.6876531,48.2296212]}}