{"type":"Feature","properties":{"Gebäude":"ja","email":"mail@gemuesehof-niederfeld.de","fax":"+49 8459 30022","Telefon":"+49 8459 1522","shop":"farm","Quelle":"HiRes aerial imagery"},"name":"Gemüsehof Niederfeld","address":{"street":"Rothenturmer Straße","housenumber":"24","postcode":"85053","city":"Ingolstadt Niederfeld"},"opening_hours":"Mo-Fr 08:00-12:30,14:00-17:30; Sa 08:00-12:00","website":"http://www.gemuesehof-niederfeld.de","property":"farm","id":"way/30906268","geometry":{"type":"Point","coordinates":[11.4722212,48.7334335]}}