{"type":"Feature","id":"node/13116916994","properties":{"addr:city":"Hessen","addr:postcode":"38835","addr:street":"Leipziger Straße","amenity":"vending_machine","currency:EUR":"yes","height":"2","image":"https://imgur.com/MhJ0wUL","indoor":"no","last_checked":"2025-09-03","operator":"SnackAttack Christoph Ritzau","payment:cash":"yes","payment:coins":"yes","payment:credit_cards":"yes","payment:debit_cards":"yes","payment:notes":"yes","phone":"+49 176 20495992","vending":"drinks;food;sweets","id":"node/13116916994"},"geometry":{"type":"Point","coordinates":[10.7773166,52.0194603]}}