{"type":"Feature","properties":{"brand":"Demeter","contact:email":"info@schanzenhof-online.de","contact:fax":"+49 5691 629748","contact:Telefon":"+49 5691 629745","Betreiber":"Stefanie Müller & Tobias Hofius GbR","Biologisch":"nur","shop":"farm"},"name":"Schanzenhof","address":{"street":"Schanzenhof","housenumber":"1","postcode":"34454","city":"Bad Arolsen"},"opening_hours":"Fr 15:00-18:00","property":"farm","id":"node/3460946117","geometry":{"type":"Point","coordinates":[9.0018312,51.3952509]}}