{"type":"Feature","properties":{"email":"stall.luedi@vtxmail.ch","note":"Eier, Äpfel, Kirschen, Zwetschgen, Nüsse. Pferdepension, Reithalle, Aussenplatz Reitschule: Reitstunden, Pony Reiten.","Betreiber":"Jürg und Diana Lüdi-Betge","Biologisch":"no","Telefon":"+41 61 721 87 17","shop":"farm","Quelle":"http://www.landwirtschaft-bielbenken.ch/bauernhof/luedi_juerg/index.php"},"name":"Hof Jürg Lüdi","address":{"street":"Hauptstrasse","housenumber":"31","postcode":"4105","city":"Biel-Benken"},"opening_hours":"täglich Selbstbedienung","website":"http://www.stall-luedi.com/","property":"farm","id":"node/4941861313","geometry":{"type":"Point","coordinates":[7.5293971,47.5068208]}}