{"type":"Feature","id":"node/4947162544","properties":{"addr:city":"Metzerlen","addr:housenumber":"3","addr:postcode":"4116","addr:street":"Hauptstrasse","description":"Marktstand mit verschiedenen Broten, Zopf, Konfitüre, Sirup, sterilisierte Früchte und Obst, Eier, Süss-Saures, Pesto, Tapenaden, Kirschen, Himbeeren, Kartoffeln, Nüsse, verschiedene Gewürzessige und -öle, Kirsch, Eierkirsch, Liköre sowie Geschenkkörbe.","email":"ida.schaffter@gmail.com;schaffterkurt@hotmail.com","name":"Chirsgartehof","opening_hours":"Mo-Fr 16:00-18:00; Sa 04:00-15:00; PH off \"Hofladen\" || Mo-Su 00:00-24:00 \"Self-Service Marktstand\"","operator":"Kurt und Ida Schaffter-Signer","organic":"no","phone":"+41 61 731 23 36","shop":"farm","source":"http://www.leimental.ch/Joomla3leimental/index.php/sehenswuerdigkeit5/10-leimental/14-frisch-vom-bauernhof","website":"http://chirsgartehof.ch/","id":"node/4947162544"},"geometry":{"type":"Point","coordinates":[7.4653478,47.4661484]}}