{"type":"Feature","id":"node/11327761090","properties":{"addr:city":"Treuenbrietzen","addr:housenumber":"64","addr:postcode":"14929","addr:street":"Bardenitzer Dorfstraße","addr:suburb":"Bardenitz","name":"Bardenitzer Hofladen","opening_hours":"Mar Th-Sa 09:00-18:00; Apr-Jun 09:00-18:00; Jul,Sep-Nov We-Su 09:00-18:00; Dec 01-23 Mo-Su 09:00-18:00","organic":"yes","payment:cash":"yes","payment:credit_cards":"yes","phone":"+49 33748 15581","shop":"farm","website":"https://bardenitzer-hofladen.de","wheelchair":"yes","id":"node/11327761090"},"geometry":{"type":"Point","coordinates":[12.9418522,52.0731848]}}