{"type":"Feature","id":"node/4546401367","properties":{"addr:city":"Erlangen","addr:country":"DE","addr:housenumber":"2","addr:postcode":"91056","addr:street":"Brühl","description":"Aus eigenem Anbau: Kartoffeln, Apfelsaft Speise-, Zier- und Halloween-Kürbisse, Zugekauft: Honig, Nudeln,Fruchtaufstriche, Eier, eingewecktes Gemüse, Kürbiskernprodukte, Rapsöl, Brennholz, ...","email":"hofladen@wirths-hof.de","name":"Wirth's Hof","opening_hours":"PH,Mo-Su 09:00-20:00","payment:cash":"yes","shop":"farm","website":"www.wirths-hof.de","id":"node/4546401367"},"geometry":{"type":"Point","coordinates":[10.9378276,49.6269831]}}