{"type":"Feature","id":"way/327796552","properties":{"addr:city":"Priestewitz","addr:housenumber":"21","addr:postcode":"01561","addr:street":"Bergstraße","addr:suburb":"Blattersleben","building":"yes","contact:email":"obsthof-ibisch@freenet.de","contact:phone":"+49 35267 50019","name":"Obsthof Ibisch","opening_hours":"Mo-Fr 09:00-18:00; Sa 09:00-13:00","shop":"farm","website":"https://www.obsthof-ibisch.de","id":"way/327796552"},"geometry":{"type":"Point","coordinates":[13.4647979,51.2402231]}}