{"type":"Feature","id":"node/2844979116","properties":{"addr:city":"Baden-Baden","addr:country":"DE","addr:housenumber":"5","addr:postcode":"76532","addr:street":"Rathausplatz","addr:suburb":"Haueneberstein","name":"Eberschder Dorfladen","old_name":"Metzgerei Kahles","opening_hours":"Mo-Su 07:00-22:00","operator":"Landseehof","shop":"farm","website":"https://www.landseehof.de/dorfladen-haueneberstein","wheelchair":"no","id":"node/2844979116"},"geometry":{"type":"Point","coordinates":[8.222354,48.8061141]}}