{"type":"Feature","id":"node/13325008339","properties":{"amenity":"vending_machine","check_date":"2025-11-22","indoor":"yes","name":"Ein Laden in Marjoß","opening_hours":"Mo-Su,PH 00:00-00:00","payment:cash":"yes","payment:coins":"yes","payment:credit_cards":"yes","payment:debit_cards":"yes","shop":"yes","vending":"drinks;food;bread;milk;ice_cream;eggs","website":"https://einladenimspessart.de/","wheelchair":"no","id":"node/13325008339"},"geometry":{"type":"Point","coordinates":[9.51322,50.2580159]}}