{"type":"Feature","properties":{"email":"humpelihof@bluewin.ch,  web@bauernschlau.ch","note":"Produkte saisonal im Direktverkauf: Kirschen, Äpfel, Kartoffeln, Kirsch und Rindfleisch. Galloway-Rindfleisch im Mischpaket, in Portionen aufgeteilt, etikettiert und vakuumiert.","Betreiber":"Christoph und Susanne Sigrist-Bossart","Biologisch":"ja","Telefon":"+41 61 901 52 90","shop":"farm","Quelle":"https://www.knospehof.ch/bio/humpelihof"},"name":"Hümpelihof","address":{"street":"Hümpelihof","housenumber":"7","postcode":"4144","city":"Füllinsdorf"},"opening_hours":"nach Vereinbarung","website":"http://www.bauernschlau.ch/pages/hof1.html","property":"farm","id":"node/4950554367","geometry":{"type":"Point","coordinates":[7.7346305,47.5006267]}}