{"type":"Feature","id":"node/920269145","properties":{"addr:city":"Arnsberg","addr:country":"DE","addr:housenumber":"4","addr:postcode":"59755","addr:street":"Neheimer Markt","contact:phone":"+49 2932 6393367","contact:website":"https://www.hofladen-sauerland.de","name":"Hofladen Sauerland","opening_hours":"Mo-Fr 09:00-18:30; Sa 09:00-16:00","operator":"Christian Schulte Vertriebsgesellschaft Sauerland UG (haftungsbeschränkt)","shop":"farm","wheelchair":"yes","id":"node/920269145"},"geometry":{"type":"Point","coordinates":[7.9599976,51.4530942]}}