{"type":"Feature","properties":{"email":"zimmermann@villigen.com","note":"Weissweine, Rotweine, Traubensaft, Früchte, Kartoffeln, Fleischwaren: Bratwürste, Rauchwürste, Saft & Sirup.","Betreiber":"Hans Rudolf und Claudia Zimmermann-Kocher","Biologisch":"no","Telefon":"+41 56 290 20 80","shop":"farm","Quelle":"https://www.vomhof.ch/hof-suche/detailansicht/farm/chlopfis-bauernhof/"},"name":"Chlopfi's Bauernhof","address":{"street":"Neuzelg","housenumber":"362","postcode":"5234","city":"Villigen"},"opening_hours":"nach Vereinbarung, Online-Versand","website":"http://chlopfi.ch/ &  http://www.swisswagyu.ch","property":"farm","id":"node/4961915408","geometry":{"type":"Point","coordinates":[8.2189759,47.5196202]}}