{"type":"Feature","id":"node/12293846063","properties":{"addr:city":"Teisendorf","addr:country":"DE","addr:housenumber":"2","addr:postcode":"83317","addr:street":"Egelham","contact:email":"info@hoisseis-biohofladen.de","contact:mobile":"+49 160 9724 7148","contact:website":"https://www.hoisseis-biohofladen.de/hofladen/","description":"Hofladen mit Rindfleisch, Wurst, Käse, eingelegtem Käse, Honig, Marmeladen und weiteren saisonal wechselnde Angeboten aus eigener Produktion.","name":"Hoißeis Hoflanden","opening_hours":"Mo-Su 08:00-20:00","operator":"Carina und Johannes Hoiß","organic":"only","self_service":"only","shop":"farm","id":"node/12293846063"},"geometry":{"type":"Point","coordinates":[12.8497177,47.825867]}}