{"type":"Feature","id":"node/5678951879","properties":{"addr:city":"Leubsdorf","addr:country":"DE","addr:housenumber":"51","addr:postcode":"09573","addr:street":"Grünhainichener Straße","addr:suburb":"Marbach","contact:email":"kontakt@gefluegelhof-berger.de","contact:phone":"+49 37291 61922","contact:website":"https://gefluegelhof-berger.de/","name":"Hofladen Marbach","opening_hours":"Mo-Fr 14:00-17:00; Sa 09:00-12:00; Su,PH off","operator":"Geflügelhof Berger","shop":"farm","wheelchair":"limited","id":"node/5678951879"},"geometry":{"type":"Point","coordinates":[13.1350405,50.7910337]}}