{"type":"Feature","id":"way/124449351","properties":{"addr:city":"Aschaffenburg","addr:country":"DE","addr:housenumber":"27","addr:postcode":"63743","addr:street":"Unterhainstraße","building":"yes","email":"info@hofladen-brunner.de","name":"Hofladen Brunner","opening_hours":"Mo,We 09:00-14:00; Tu,Fr,Th 09:00-18:30; Sa 09:00-13:00","phone":"+49 06021 438 3087","shop":"farm","website":"https://hofladen-brunner.de/","id":"way/124449351"},"geometry":{"type":"Point","coordinates":[9.1531845,49.9598319]}}