{"type":"Feature","id":"node/4921079948","properties":{"addr:city":"Allschwil","addr:housenumber":"5b","addr:postcode":"4123","addr:street":"Lörzbachmühle","email":"mosimannfarm-bl@bluewin.ch","name":"Hof Lörzbachmühle","note":"Erdbeeren ab Hof und zum Selberpflücken.  Frischer Knoblauch. Lörzbachtaler Festraum: Feste feiern in gemütlicher Umgebung Lörzbachtaler-Beef: im Mischpaket vom  Simmentaler Jungrind kaufen. Lamatrekking.","opening_hours":"nach Vereinbarung","operator":"Ruedi und Elisabeth Mosimann","organic":"no","phone":"+41 61 481 45 23","shop":"farm","source":"https://www.baselland-tourismus.ch/download/4003/Ab_ufs_Land_-_Panoramakarte.pdf","website":"http://www.simmentaler.ch/","id":"node/4921079948"},"geometry":{"type":"Point","coordinates":[7.5098192,47.5452515]}}