{"type":"Feature","id":"node/10899593854","properties":{"addr:city":"Kaumberg","addr:housenumber":"40","addr:place":"Markt","addr:postcode":"2560","amenity":"restaurant","cuisine":"austrian","email":"familie.schuh@gmx.net","name":"Familie Schuh","opening_hours:kitchen":"see online-calendar (\"ausg'steckt\")","opening_hours:office":"Sa 08-16","phone":"+43 2765 334","restaurant":"buschenschank","shop":"farm","website":"https://heurigenkalender.niederoesterreich.at/182416/ausgsteckt-is","id":"node/10899593854"},"geometry":{"type":"Point","coordinates":[15.8837631,48.0330097]}}