{"type":"Feature","id":"node/276049696","properties":{"addr:city":"Friedeburg","addr:country":"DE","addr:hamlet":"Bentstreek","addr:housenumber":"1","addr:postcode":"26446","addr:street":"Bentstreeker Schulweg","description":"Käse, Lammfleisch, Kaninchen, Liköre, Naturkosmetik, Schafwolle u. a. m.","email":"heike.gerbracht@heikes-moorhof.de","fax":"+49 4956 912805","name":"Heikes Moorhof","opening_hours":"Tu-Su 11:00-18:00; Mo off","operator":"Heike & Thomas Gerbracht","phone":"+49 4956 912803","shop":"farm","website":"https://www.heikes-moorhof.de/","id":"node/276049696"},"geometry":{"type":"Point","coordinates":[7.8464033,53.3711394]}}