{"type":"Feature","id":"way/452754163","properties":{"addr:city":"Hamminkeln","addr:country":"DE","addr:housenumber":"12","addr:postcode":"46499","addr:street":"Borkener Straße","building":"yes","description":"frische und hochwertige Lebensmittel von unseren eigenen Feldern und viele Spezialitäten aus unserer Hofküche,  außerdem viele weitere regionale Leckereien von benachbarten und befreundeten Landwirten, Imkern, Winzern, Bierbrauern, Schnapsbrennern, ...","name":"Hof Schäfer","opening_hours":"Mo-Fr 09:00-18:30; Sa 09:00-17:00; Su 11:00-17:00","operator":"Familie Schäfer","phone":"+49 2856 463","shop":"farm","website":"https://www.hof-schaefer.de/","id":"way/452754163"},"geometry":{"type":"Point","coordinates":[6.6825015,51.7541485]}}