{"type":"Feature","id":"way/1052303661","properties":{"addr:city":"Hagenberg im Mühlkreis","addr:housenumber":"34","addr:postcode":"4232","addr:street":"Veichter","building":"yes","name":"SB Eierhütte","opening_hours":"24/7","opening_hours:covid19":"same","operator":"Eierhof Angerer","organic":"only","payment:cash":"yes","payment:credit_cards":"yes","shop":"farm","start_date":"2019-09","website":"https://eierhof-angerer.at/","id":"way/1052303661"},"geometry":{"type":"Point","coordinates":[14.5243131,48.3696054]}}