{"type":"Feature","properties":{"email":"robert.obrist@fibl.org","note":"Wein aus Europäischen und Neuseeländischen  Weinsorten, Traubensaft.","Betreiber":"Robert Obrist","Biologisch":"ja","Telefon":"+41 56 443 33 15","shop":"farm","Quelle":"https://www.knospehof.ch/bio/obrist"},"name":"Weinbau Robert Obrist","address":{"street":"Rosenweg","housenumber":"18","postcode":"5107","city":"Schinznach-Dorf"},"opening_hours":"nach Vereinbarung","property":"farm","id":"node/4959941279","geometry":{"type":"Point","coordinates":[8.147821,47.4465118]}}