{"type":"Feature","id":"node/2735336928","properties":{"addr:city":"Karben-Kloppenheim","addr:country":"DE","addr:housenumber":"16","addr:postcode":"61184","addr:street":"Frankfurter Straße","contact:email":"info@margarethenhof.de","contact:fax":"+49 6039 9246-48","contact:phone":"+49 6039 9246-0","contact:website":"https://www.margarethenhof.de","email":"info@margarethenhof.de","image":"https://margarethenhof.de/sites/default/themes/yaml/layouts/yaml_2col_13/img/bg-outside.jpg","name":"Margarethenhof","opening_hours":"Mo-Fr 08:00-19:00; Sa 08:00-15:00","operator":"Familie Kliem","phone":"+49 6039 92460","shop":"farm","website":"https://margarethenhof.de/","id":"node/2735336928"},"geometry":{"type":"Point","coordinates":[8.7444193,50.23188]}}