{"type":"Feature","id":"node/5540840165","properties":{"addr:city":"Striegistal","addr:country":"DE","addr:housenumber":"7","addr:postcode":"09661","addr:street":"Mühlstraße","addr:suburb":"Pappendorf","contact:email":"info@schubertmuehle.de","contact:phone":"+49 37207 995881","contact:website":"https://www.schubertmuehle.de/","name":"Senfmanufaktur Schubertmühle","opening_hours":"We 10:00-18:00; Sa,Su,PH 11:00-17:00; Mo,Tu,Th,Fr off","operator":"Thomas Dietrich","product":"mustard;noodles;jam","shop":"farm","wheelchair":"no","id":"node/5540840165"},"geometry":{"type":"Point","coordinates":[13.1819743,50.9901355]}}