{"type":"Feature","id":"way/216966978","properties":{"addr:city":"Gamlitz","addr:country":"AT","addr:housenumber":"42","addr:place":"Steinbach","addr:postcode":"8462","award":"gutfinden, Gasttaxi","building":"yes","contact:email":"brennerei@tinnauer.at","contact:phone":"+43 3453 3607","name":"Fruchtbrennerei Franz Tinnauer","operator":"Tinnauer","shop":"farm","source":"GeoImage.at High-Res;TVB Südsteiermark","website":"http://www.tinnauer.at","weinmobil:note":"Bitte weinmobil:ref nicht entfernen, dient zum automatischen Update.","weinmobil:ref":"461","id":"way/216966978"},"geometry":{"type":"Point","coordinates":[15.5250598,46.6950451]}}