{"type":"Feature","properties":{"Einrichtung ":"marketplace","Letze Überprüfung":"2017-08-12","Quelle":"http://www.oehringen.de/freizeit/bummeln-und-einkaufen/oehringer-wochenmarkt.html"},"name":"Wochenmarkt Öhringen","address":{"postcode":"74613","city":"Öhringen","country":"Germany","country_code":"de"},"opening_hours":"May-Sep: We 07:00-13:00; May-Sep: Sa 07:00-12:30; Oct-Apr: We 08:00-13:00; Oct-Apr: Sa 08:00-12:30","property":"marketplace","id":"node/5030234311","geometry":{"type":"Point","coordinates":[9.5024765,49.2005105]}}