{"type":"Feature","id":"node/13196269132","properties":{"addr:city":"Erlenbach im Simmental","addr:housenumber":"366h","addr:postcode":"3762","addr:street":"Oberdorf","currency:XBT":"yes","name":"Knutti Geflügel.ch","operator":"Knutti Geflügel.ch","organic":"yes","payment:cash":"yes","payment:lightning":"yes","payment:onchain":"yes","phone":"+41798765070","shop":"farm","survey:date":"2025-10-05","website":"https://knuttigefluegel.ch/","id":"node/13196269132"},"geometry":{"type":"Point","coordinates":[7.5472467,46.6619761]}}