{"type":"Feature","id":"node/9950525445","properties":{"addr:city":"Langenwolschendorf","addr:housenumber":"7","addr:postcode":"07937","addr:street":"Am Schafteich","amenity":"vending_machine","covered":"yes","currency:EUR":"yes","currency:others":"no","name":"24h Hofladen Langenwolschendorf","opening_hours":"24/7","operator":"Landwirtschaftsbetrieb Bannasch Gärtnerei & Hofladen Langenwolschendorf","payment:coins":"yes","payment:contactless":"yes","payment:debit_cards":"yes","payment:notes":"yes","vending":"cheese;eggs;sausages;noodles;butter;canned sausages","vending:food":"yes","website":"http://www.hofladen-langenwolschendorf.de/seite/273533/24h-automat.html","id":"node/9950525445"},"geometry":{"type":"Point","coordinates":[11.9670956,50.6407775]}}