{"type":"Feature","id":"node/2901500663","properties":{"addr:city":"Wesseling","addr:country":"DE","addr:housenumber":"24","addr:postcode":"50389","addr:street":"Hagenstraße","contact:email":"hagenhof@gmx.net","contact:facebook":"https://www.facebook.com/profile.php?id=100046570455640","contact:phone":"+49 2232 51886","contact:website":"http://www.gut-hagenhof.de/hofladen.html","name":"Hagenhof","opening_hours":"Mo-Fr 09:00-18:00; Sa 09:00-13:00","operator":"Michael Lettmann Andreas Lettmann","shop":"farm","id":"node/2901500663"},"geometry":{"type":"Point","coordinates":[6.9506081,50.830841]}}