{"type":"Feature","id":"node/1407115633","properties":{"addr:city":"Bornheim","addr:country":"DE","addr:housenumber":"31","addr:postcode":"53332","addr:street":"Weidenpeschweg","check_date:opening_hours":"2022-10-29","email":"hofladen@biohof-bursch.de","name":"Hofladen Biohof Bursch","opening_hours":"Mo-Fr 08:30-18:30; Sa 08:30-15:00","organic":"yes","phone":"+49 2227 9199 14","shop":"farm","website":"https://www.biohof-bursch.de/","id":"node/1407115633"},"geometry":{"type":"Point","coordinates":[6.9559139,50.7677]}}