{"type":"Feature","id":"node/11111323294","properties":{"addr:city":"Gossau SG","addr:place":"Mädertal","addr:postcode":"9200","check_date":"2023-08-13","check_date:currency:XBT":"2025-07-02","currency:XBT":"yes","delivery":"yes","delivery:zone":"DE","description":"Wochenmarkt:\nSamstag: 08:00-11:30 Uhr","name":"Bio Hof Mädertal","opening_hours":"Mo-Su 08:00-21:00","organic":"only","payment:cash":"yes","payment:lightning":"no","payment:onchain":"yes","payment:twint":"yes","produce":"vegetables,potatoes,aspberry","shop":"farm","website":"https://biohofmaedertal.ch/","id":"node/11111323294"},"geometry":{"type":"Point","coordinates":[9.2332648,47.4150974]}}