{"type":"Feature","id":"node/6681561573","properties":{"addr:city":"Oberrot","addr:country":"DE","addr:housenumber":"5","addr:postcode":"74420","addr:street":"Völkleswaldweg","email":"voelkleswaldhof@t-online.de","name":"Völkleswaldhof","old_operator":"Anja und Pius Frey","operator":"Stiftung Aktion Kulturland, Köln","organic":"yes","phone":"+49 1575 4973145","shop":"farm","website":"https://www.voelkleswaldhof.de","id":"node/6681561573"},"geometry":{"type":"Point","coordinates":[9.6956487,49.0073207]}}