{"type":"Feature","id":"node/9316333772","properties":{"addr:city":"Neukirchen-Vluyn","addr:housenumber":"77","addr:postcode":"47506","addr:street":"Littardweg","description":"Kardierte Wolle zum Filzen, als Kissen- oder Deckenfüllung. Strickwolle natur- und pflanzengefärbt, Socken, Pullover, Westen, Wolldecken, Yogamatten, Rucksäcke und Taschen aus Wollfilz","name":"Die Schaf-Gabe","opening_hours":"We 15:00-17:00, Sa 10:00-14:00","operator":"Angelika Girndt","phone":"+49 2845 33347","shop":"farm","website":"https://www.schafgabe.de/","id":"node/9316333772"},"geometry":{"type":"Point","coordinates":[6.50356,51.4594445]}}