{"type":"Feature","id":"node/11750622827","properties":{"addr:city":"Vittel","addr:postcode":"88800","addr:street":"Galerie Thermale","amenity":"marketplace","building":"no","check_date:opening_hours":"2024-03-21","name":"Marché de l'Artisanat et du Goût","opening_hours":"May,Jun,Sep: Su[1] 10:00-18:00, Jul, Aug: Su[1,3] 10:00-18:00","opening_hours:url":"https://www.contrextourisme.com/offres/marche-de-lartisanat-et-du-gout-vittel-fr-3505409/","product":"food","source:opening_hours":"https://www.ville-vittel.fr/fr/foires-et-marches.html","id":"node/11750622827"},"geometry":{"type":"Point","coordinates":[5.9416221,48.2078296]}}