{"type":"Feature","id":"node/12291889903","properties":{"amenity":"marketplace","contact:website":"https://sablonantiquesmarket.be/","name":"Marché des Antiquités du Sablon - Antiekmarkt van de Zavel","name:en":"Sablon Antiques Market","name:fr":"Marché des Antiquités du Sablon","name:nl":"Antiekmarkt van de Zavel","opening_hours":"Sa 09:00-17:00; Su 09:00-15:00","start_date":"1960-04-03","wikidata":"Q130702932","id":"node/12291889903"},"geometry":{"type":"Point","coordinates":[4.3557513,50.840528]}}