{"type":"Feature","id":"way/334427029","properties":{"addr:city":"Kevelaer","addr:housenumber":"10","addr:postcode":"47626","addr:street":"Hestert","building":"yes","delivery":"yes","email":"info@biohofetzold.de","name":"Biohof Etzold","opening_hours":"Dienstag und Donnerstag 14 - 19 Uhr, Freitag 9 - 19 Uhr, Samstag 9 - 14 Uhr","operator":"Jonas Etzold","organic":"only","phone":"+49 2832 8237","ref:oeko_modellregion":"Niederrhein","shop":"farm","website":"https://www.biohofetzold.de/","id":"way/334427029"},"geometry":{"type":"Point","coordinates":[6.2951922,51.604427]}}