{"type":"Feature","properties":{"email":"info@silberdistel-kost.ch","note":"Rindfleisch (Angus), Ziegenfleisch (Burenziege), Schweinefleisch (Distelschwein),","Betreiber":"Cäsar und Lena Bürgi","Biologisch":"ja","Telefon":"+41 62 390 03 05","shop":"farm","Quelle":"http://demeter.ch/hof-finden/"},"name":"Hof Obere Wies","address":{"street":"Obere Wies","housenumber":"242","postcode":"4718","city":"Holderbank (SO)"},"opening_hours":"Bestellungen telefonisch oder per E-mail. Sa: 8-13 Uhr Matthäusmarkt Basel","website":"http://silberdistel-kost.ch/","property":"farm","id":"node/4958385387","geometry":{"type":"Point","coordinates":[7.7613973,47.3285423]}}